nodeconductor_killbill/__init__.py
nodeconductor_killbill/admin.py
nodeconductor_killbill/apps.py
nodeconductor_killbill/backend.py
nodeconductor_killbill/extension.py
nodeconductor_killbill/filters.py
nodeconductor_killbill/handlers.py
nodeconductor_killbill/log.py
nodeconductor_killbill/models.py
nodeconductor_killbill/perms.py
nodeconductor_killbill/serializers.py
nodeconductor_killbill/tasks.py
nodeconductor_killbill/urls.py
nodeconductor_killbill/views.py
nodeconductor_killbill/migrations/0001_initial.py
nodeconductor_killbill/migrations/__init__.py
nodeconductor_killbill/templates/admin/nodeconductor_killbill/change_list.html
nodeconductor_killbill/templates/nodeconductor_killbill/annual_report.html
nodeconductor_killbill/templates/nodeconductor_killbill/invoice.html
nodeconductor_killbill/templates/nodeconductor_killbill/usage_invoice.html
nodeconductor_killbill-0.5.1.dist-info/DESCRIPTION.rst
nodeconductor_killbill-0.5.1.dist-info/METADATA
nodeconductor_killbill-0.5.1.dist-info/RECORD
nodeconductor_killbill-0.5.1.dist-info/WHEEL
nodeconductor_killbill-0.5.1.dist-info/entry_points.txt
nodeconductor_killbill-0.5.1.dist-info/metadata.json
nodeconductor_killbill-0.5.1.dist-info/top_level.txt
