Metadata-Version: 2.0
Name: nodeconductor-killbill
Version: 0.5.1
Summary: NodeConductor KillBill allows to make invoices via KillBill
Home-page: http://nodeconductor.com
Author: OpenNode Team
Author-email: info@opennodecloud.com
License: UNKNOWN
Platform: UNKNOWN
Classifier: Framework :: Django
Classifier: Intended Audience :: Developers
Classifier: Intended Audience :: System Administrators
Classifier: Operating System :: OS Independent
Classifier: License :: OSI Approved :: MIT License
Requires-Dist: Pillow (>=2.0.0,<3.0.0)
Requires-Dist: html5lib (<0.99999999)
Requires-Dist: lxml (>=3.2)
Requires-Dist: nodeconductor (>=0.107.0)
Requires-Dist: xhtml2pdf (==0.0.6)
Provides-Extra: dev
Requires-Dist: Sphinx (==1.2.2); extra == 'dev'
